odoo/addons/l10n_fr_department_oversea/README.rst
odoo/addons/l10n_fr_department_oversea/__init__.py
odoo/addons/l10n_fr_department_oversea/__manifest__.py
odoo/addons/l10n_fr_department_oversea/post_install.py
odoo/addons/l10n_fr_department_oversea/data/res_country_department.xml
odoo/addons/l10n_fr_department_oversea/data/res_country_state.xml
odoo/addons/l10n_fr_department_oversea/i18n/l10n_fr_department_oversea.pot
odoo/addons/l10n_fr_department_oversea/readme/CONTRIBUTORS.rst
odoo/addons/l10n_fr_department_oversea/readme/DESCRIPTION.rst
odoo/addons/l10n_fr_department_oversea/static/description/icon.png
odoo/addons/l10n_fr_department_oversea/static/description/index.html
odoo/addons/l10n_fr_department_oversea/tests/__init__.py
odoo/addons/l10n_fr_department_oversea/tests/test_department_oversea.py
odoo14_addon_l10n_fr_department_oversea-14.0.1.0.1.dist-info/METADATA
odoo14_addon_l10n_fr_department_oversea-14.0.1.0.1.dist-info/WHEEL
odoo14_addon_l10n_fr_department_oversea-14.0.1.0.1.dist-info/top_level.txt
odoo14_addon_l10n_fr_department_oversea-14.0.1.0.1.dist-info/RECORD
